{
  "data": [
    {
      "id": 5638,
      "name": "Thị trấn Cao Lộc"
    },
    {
      "id": 5639,
      "name": "Thị trấn Đồng Đăng"
    },
    {
      "id": 5640,
      "name": "Xã Bảo Lâm"
    },
    {
      "id": 5641,
      "name": "Xã Bình Trung"
    },
    {
      "id": 5642,
      "name": "Xã Cao Lâu"
    },
    {
      "id": 5643,
      "name": "Xã Công Sơn"
    },
    {
      "id": 5644,
      "name": "Xã Gia Cát"
    },
    {
      "id": 5645,
      "name": "Xã Hải Yến"
    },
    {
      "id": 5646,
      "name": "Xã Hòa Cư"
    },
    {
      "id": 5647,
      "name": "Xã Hồng Phong"
    },
    {
      "id": 5648,
      "name": "Xã Hợp Thành"
    },
    {
      "id": 5649,
      "name": "Xã Lộc Yên"
    },
    {
      "id": 5650,
      "name": "Xã Mẫu Sơn"
    },
    {
      "id": 5651,
      "name": "Xã Phú Xá"
    },
    {
      "id": 5652,
      "name": "Xã Song Giáp"
    },
    {
      "id": 5653,
      "name": "Xã Tân Liên"
    },
    {
      "id": 5654,
      "name": "Xã Tân Thành"
    },
    {
      "id": 5655,
      "name": "Xã Thạch Đạn"
    },
    {
      "id": 5656,
      "name": "Xã Thanh Lòa"
    },
    {
      "id": 5657,
      "name": "Xã Thụy Hùng"
    },
    {
      "id": 5658,
      "name": "Xã Xuân Long"
    },
    {
      "id": 5659,
      "name": "Xã Xuất Lễ"
    },
    {
      "id": 5660,
      "name": "Xã Yên Trạch"
    }
  ]
}
