{
  "data": [
    {
      "id": 1854,
      "name": "Xã Hòa Bắc"
    },
    {
      "id": 1855,
      "name": "Xã Hòa Châu"
    },
    {
      "id": 1856,
      "name": "Xã Hòa Khương"
    },
    {
      "id": 1857,
      "name": "Xã Hòa Liên"
    },
    {
      "id": 1858,
      "name": "Xã Hòa Nhơn"
    },
    {
      "id": 1859,
      "name": "Xã Hòa Ninh"
    },
    {
      "id": 1860,
      "name": "Xã Hòa Phong"
    },
    {
      "id": 1861,
      "name": "Xã Hòa Phú"
    },
    {
      "id": 1862,
      "name": "Xã Hòa Phước"
    },
    {
      "id": 1863,
      "name": "Xã Hòa Sơn"
    },
    {
      "id": 1864,
      "name": "Xã Hòa Tiến"
    }
  ]
}
