{
  "data": [
    {
      "id": 10379,
      "name": "Phường Bến Nghé"
    },
    {
      "id": 10380,
      "name": "Phường Bến Thành"
    },
    {
      "id": 10381,
      "name": "Phường Cầu Kho"
    },
    {
      "id": 10382,
      "name": "Phường Cầu Ông Lãnh"
    },
    {
      "id": 10383,
      "name": "Phường Cô Giang"
    },
    {
      "id": 10384,
      "name": "Phường Đa Kao"
    },
    {
      "id": 10385,
      "name": "Phường Nguyễn Cư Trinh"
    },
    {
      "id": 10386,
      "name": "Phường Nguyễn Thái Bình"
    },
    {
      "id": 10387,
      "name": "Phường Phạm Ngũ Lão"
    },
    {
      "id": 10388,
      "name": "Phường Tân Định"
    }
  ]
}
