{
  "data": [
    {
      "id": 8757,
      "name": "Thị trấn Yên Châu"
    },
    {
      "id": 8758,
      "name": "Xã Chiềng Đông"
    },
    {
      "id": 8759,
      "name": "Xã Chiềng Hặc"
    },
    {
      "id": 8760,
      "name": "Xã Chiềng Khoi"
    },
    {
      "id": 8761,
      "name": "Xã Chiềng On"
    },
    {
      "id": 8762,
      "name": "Xã Chiềng Pằn"
    },
    {
      "id": 8763,
      "name": "Xã Chiềng Sàng"
    },
    {
      "id": 8764,
      "name": "Xã Chiềng Tương"
    },
    {
      "id": 8765,
      "name": "Xã Lóng Phiêng"
    },
    {
      "id": 8766,
      "name": "Xã Mường Lựm"
    },
    {
      "id": 8767,
      "name": "Xã Phiêng Khoài"
    },
    {
      "id": 8768,
      "name": "Xã Sập Vạt"
    },
    {
      "id": 8769,
      "name": "Xã Tú Nang"
    },
    {
      "id": 8770,
      "name": "Xã Viêng Lán"
    },
    {
      "id": 8771,
      "name": "Xã Yên Sơn"
    }
  ]
}
